invenio_xrootd/__init__.py
invenio_xrootd/errors.py
invenio_xrootd/ext.py
invenio_xrootd/storage.py
invenio_xrootd-2.0.0a2.dist-info/AUTHORS.rst
invenio_xrootd-2.0.0a2.dist-info/LICENSE
invenio_xrootd-2.0.0a2.dist-info/METADATA
invenio_xrootd-2.0.0a2.dist-info/WHEEL
invenio_xrootd-2.0.0a2.dist-info/entry_points.txt
invenio_xrootd-2.0.0a2.dist-info/top_level.txt
invenio_xrootd-2.0.0a2.dist-info/RECORD
